README.md
setup.py
OpenNMT_py_svx.egg-info/PKG-INFO
OpenNMT_py_svx.egg-info/SOURCES.txt
OpenNMT_py_svx.egg-info/dependency_links.txt
OpenNMT_py_svx.egg-info/entry_points.txt
OpenNMT_py_svx.egg-info/requires.txt
OpenNMT_py_svx.egg-info/top_level.txt
onmt/__init__.py
onmt/model_builder.py
onmt/opts.py
onmt/train_single.py
onmt/trainer.py
onmt/bin/__init__.py
onmt/bin/average_models.py
onmt/bin/preprocess.py
onmt/bin/release_model.py
onmt/bin/server.py
onmt/bin/train.py
onmt/bin/translate.py
onmt/decoders/__init__.py
onmt/decoders/cnn_decoder.py
onmt/decoders/decoder.py
onmt/decoders/ensemble.py
onmt/decoders/transformer.py
onmt/encoders/__init__.py
onmt/encoders/audio_encoder.py
onmt/encoders/cnn_encoder.py
onmt/encoders/encoder.py
onmt/encoders/image_encoder.py
onmt/encoders/mean_encoder.py
onmt/encoders/rnn_encoder.py
onmt/encoders/transformer.py
onmt/inputters/__init__.py
onmt/inputters/audio_dataset.py
onmt/inputters/datareader_base.py
onmt/inputters/dataset_base.py
onmt/inputters/image_dataset.py
onmt/inputters/inputter.py
onmt/inputters/text_dataset.py
onmt/inputters/vec_dataset.py
onmt/models/__init__.py
onmt/models/model.py
onmt/models/model_saver.py
onmt/models/sru.py
onmt/models/stacked_rnn.py
onmt/modules/__init__.py
onmt/modules/average_attn.py
onmt/modules/conv_multi_step_attention.py
onmt/modules/copy_generator.py
onmt/modules/embeddings.py
onmt/modules/gate.py
onmt/modules/global_attention.py
onmt/modules/multi_headed_attn.py
onmt/modules/position_ffn.py
onmt/modules/source_noise.py
onmt/modules/sparse_activations.py
onmt/modules/sparse_losses.py
onmt/modules/structured_attention.py
onmt/modules/util_class.py
onmt/modules/weight_norm.py
onmt/tests/__init__.py
onmt/tests/test_attention.py
onmt/tests/test_audio_dataset.py
onmt/tests/test_beam_search.py
onmt/tests/test_copy_generator.py
onmt/tests/test_embeddings.py
onmt/tests/test_greedy_search.py
onmt/tests/test_image_dataset.py
onmt/tests/test_models.py
onmt/tests/test_preprocess.py
onmt/tests/test_simple.py
onmt/tests/test_structured_attention.py
onmt/tests/test_text_dataset.py
onmt/tests/test_translation_server.py
onmt/tests/utils_for_tests.py
onmt/translate/__init__.py
onmt/translate/beam_search.py
