Metadata-Version: 2.1
Name: OpenNMT-py-svx
Version: 1.1.1
Summary: A python implementation of OpenNMT - Modified by Sonvx by adding a write_out flag
Home-page: UNKNOWN
License: UNKNOWN
Project-URL: Documentation, http://opennmt.net/OpenNMT-py/
Project-URL: Forum, http://forum.opennmt.net/
Project-URL: Gitter, https://gitter.im/OpenNMT/OpenNMT-py
Project-URL: Source, https://github.com/OpenNMT/OpenNMT-py/
Platform: UNKNOWN
